otex/__init__.py
otex/config.py
otex/analysis/__init__.py
otex/analysis/distributions.py
otex/analysis/sensitivity.py
otex/analysis/uncertainty.py
otex/analysis/visualization.py
otex/core/__init__.py
otex/core/cycles.py
otex/core/fluids.py
otex/core/mixtures.py
otex/data/__init__.py
otex/data/cmems.py
otex/data/multi_depth.py
otex/data/netcdf.py
otex/economics/__init__.py
otex/economics/costs.py
otex/economics/optimization.py
otex/plant/__init__.py
otex/plant/components.py
otex/plant/off_design_analysis.py
otex/plant/operation.py
otex/plant/sizing.py
otex/plant/utils.py
otex-0.1.1.dist-info/METADATA
otex-0.1.1.dist-info/WHEEL
otex-0.1.1.dist-info/top_level.txt
otex-0.1.1.dist-info/RECORD
