Metadata-Version: 2.4
Name: otex
Version: 0.1.1
Summary: OTEX - Ocean Thermal Energy eXchange: OTEC plant design, simulation, and analysis
Author: OTEX Development Team
License: MIT
Project-URL: Homepage, https://github.com/otex-dev/otex
Project-URL: Documentation, https://otex.readthedocs.io
Project-URL: Repository, https://github.com/otex-dev/otex
Project-URL: Issues, https://github.com/otex-dev/otex/issues
Keywords: OTEC,ocean thermal energy,renewable energy,thermodynamic cycles,power plant,simulation
Classifier: Development Status :: 4 - Beta
Classifier: Intended Audience :: Science/Research
Classifier: License :: OSI Approved :: MIT License
Classifier: Operating System :: OS Independent
Classifier: Programming Language :: Python :: 3
Classifier: Programming Language :: Python :: 3.9
Classifier: Programming Language :: Python :: 3.10
Classifier: Programming Language :: Python :: 3.11
Classifier: Programming Language :: Python :: 3.12
Classifier: Topic :: Scientific/Engineering
Classifier: Topic :: Scientific/Engineering :: Physics
Requires-Python: >=3.9
Requires-Dist: numpy>=1.20
Requires-Dist: pandas>=1.3
Requires-Dist: scipy>=1.7
Requires-Dist: matplotlib>=3.4
Requires-Dist: tables>=3.6
Requires-Dist: xarray>=0.19
Requires-Dist: netCDF4>=1.5
Requires-Dist: tqdm>=4.60
Provides-Extra: coolprop
Requires-Dist: CoolProp>=6.4; extra == "coolprop"
Provides-Extra: uncertainty
Requires-Dist: SALib>=1.4.0; extra == "uncertainty"
Provides-Extra: dev
Requires-Dist: pytest>=7.0; extra == "dev"
Requires-Dist: pytest-cov>=4.0; extra == "dev"
Requires-Dist: ruff>=0.1; extra == "dev"
Requires-Dist: build>=1.0; extra == "dev"
Requires-Dist: twine>=4.0; extra == "dev"
Provides-Extra: docs
Requires-Dist: sphinx>=5.0; extra == "docs"
Requires-Dist: sphinx-rtd-theme>=1.0; extra == "docs"
Requires-Dist: myst-parser>=0.18; extra == "docs"
Provides-Extra: all
Requires-Dist: CoolProp>=6.4; extra == "all"
Requires-Dist: SALib>=1.4.0; extra == "all"
Requires-Dist: pytest>=7.0; extra == "all"
Requires-Dist: pytest-cov>=4.0; extra == "all"
